LICENSE
graphene_django_jwt_middleware/__init__.py
graphene_django_jwt_middleware/exceptions.py
graphene_django_jwt_middleware/middleware.py
graphene_django_jwt_middleware-0.0.7.dist-info/LICENSE
graphene_django_jwt_middleware-0.0.7.dist-info/WHEEL
graphene_django_jwt_middleware-0.0.7.dist-info/METADATA
graphene_django_jwt_middleware-0.0.7.dist-info/RECORD
