Metadata-Version: 2.1
Name: graphene-django-jwt-middleware
Version: 0.0.7
Summary: Middleware to check JWT validation in GraphQL schemas
Home-page: https://github.com/instruct-br/graphene-django-jwt-middleware
License: MIT
Keywords: graphene,django,jwt,middleware,graphql
Author: Instruct Developers
Author-email: oss@instruct.com.br
Requires-Python: >=3.6,<4.0
Classifier: License :: OSI Approved :: MIT License
Classifier: Operating System :: OS Independent
Classifier: Programming Language :: Python :: 3
Classifier: Programming Language :: Python :: 3.6
Classifier: Programming Language :: Python :: 3.7
Classifier: Programming Language :: Python :: 3.8
Classifier: Programming Language :: Python :: 3.9
Classifier: Programming Language :: Python :: 3.10
Classifier: Programming Language :: Python :: 3.11
Classifier: Programming Language :: Python :: 3
Requires-Dist: django
Requires-Dist: pyjwt (>=2.4.0,<3.0.0)
Project-URL: Repository, https://github.com/instruct-br/graphene-django-jwt-middleware
